lamina/__init__.py
lamina/agent_config.py
lamina/build_manager.py
lamina/config_loader.py
lamina/infrastructure_config.py
lamina/infrastructure_template_engine.py
lamina/infrastructure_values.py
lamina/logger.py
lamina/logging_config.py
lamina/system_config.py
lamina/api/__init__.py
lamina/api/server.py
lamina/api/unified_server.py
lamina/api/certs/export_ios_cert.sh
lamina/api/certs/generate_certs.sh
lamina/api/certs/generate_service_certs.sh
lamina/backends/__init__.py
lamina/backends/base.py
lamina/backends/huggingface.py
lamina/backends/ollama.py
lamina/cli/__init__.py
lamina/cli/agent_cli.py
lamina/cli/main.py
lamina/cli/sanctuary_cli.py
lamina/cli/templates.py
lamina/cli/unified_cli.py
lamina/coordination/__init__.py
lamina/coordination/agent_coordinator.py
lamina/coordination/constraint_engine.py
lamina/coordination/intent_classifier.py
lamina/coordination/intent_router.py
lamina/infrastructure/docker-compose-unified.yml.template
lamina/infrastructure/docker-compose.yml.template
lamina/infrastructure/docker/chromadb/Dockerfile
lamina/infrastructure/docker/chromadb/chroma-config.yaml
lamina/infrastructure/docker/ollama/Dockerfile.template
lamina/infrastructure/docker/ollama/entrypoint.sh.template
lamina/infrastructure/docker/promtail/config.yml
lamina/infrastructure/grafana/provisioning/dashboards/agent-insights.json
lamina/infrastructure/grafana/provisioning/dashboards/dashboard.yml
lamina/infrastructure/grafana/provisioning/dashboards/dashboards.yml
lamina/infrastructure/grafana/provisioning/dashboards/lamina-constellation.json
lamina/infrastructure/grafana/provisioning/dashboards/lamina-logs.json
lamina/infrastructure/grafana/provisioning/dashboards/lamina.json
lamina/infrastructure/grafana/provisioning/datasources/loki.yml
lamina/infrastructure/loki/local-config.yaml
lamina/infrastructure/nginx/Dockerfile
lamina/infrastructure/nginx/nginx-unified.conf.template
lamina/infrastructure/nginx/nginx.conf.template
lamina/infrastructure/vector/Dockerfile
lamina_core-1.0.2.dist-info/METADATA
lamina_core-1.0.2.dist-info/WHEEL
lamina_core-1.0.2.dist-info/entry_points.txt
lamina_core-1.0.2.dist-info/licenses/LICENSE
lamina_core-1.0.2.dist-info/RECORD
