Metadata-Version: 2.4
Name: lamina-core
Version: 1.0.2
Summary: Breath-first framework for building presence-aware AI agent systems
Project-URL: Homepage, https://github.com/benaskins/lamina-os
Project-URL: Documentation, https://github.com/benaskins/lamina-os/blob/main/docs/
Project-URL: Repository, https://github.com/benaskins/lamina-os
Project-URL: Issues, https://github.com/benaskins/lamina-os/issues
Author-email: Ben Askins <human@getlamina.ai>, Lamina High Council <council@getlamina.ai>, Luthier <luthier@getlamina.ai>
License: MPL-2.0
License-File: LICENSE
Keywords: agents,ai,breath-first,coordination,framework,lamina,presence-aware
Classifier: Development Status :: 5 - Production/Stable
Classifier: Intended Audience :: Developers
Classifier: License :: OSI Approved :: Mozilla Public License 2.0 (MPL 2.0)
Classifier: Programming Language :: Python :: 3
Classifier: Programming Language :: Python :: 3.11
Classifier: Programming Language :: Python :: 3.12
Classifier: Programming Language :: Python :: 3.13
Classifier: Topic :: Scientific/Engineering :: Artificial Intelligence
Classifier: Topic :: Software Development :: Libraries :: Python Modules
Classifier: Topic :: Software Development :: Quality Assurance
Requires-Python: >=3.11
Requires-Dist: aiohttp>=3.11.0
Requires-Dist: click>=8.1.7
Requires-Dist: flask>=3.1.0
Requires-Dist: httpx>=0.28.0
Requires-Dist: jinja2>=3.1.6
Requires-Dist: pydantic>=2.10.0
Requires-Dist: python-dotenv>=1.0.1
Requires-Dist: pyyaml>=6.0.2
Requires-Dist: requests>=2.32.0
Requires-Dist: rich>=13.9.0
Requires-Dist: typer>=0.15.0
Requires-Dist: werkzeug>=3.1.0
Provides-Extra: ai-backends
Requires-Dist: ollama>=0.4.9; extra == 'ai-backends'
Requires-Dist: sentence-transformers>=3.3.0; extra == 'ai-backends'
Requires-Dist: torch>=2.5.0; extra == 'ai-backends'
Requires-Dist: transformers>=4.47.0; extra == 'ai-backends'
Provides-Extra: all
Requires-Dist: bandit>=1.8.0; extra == 'all'
Requires-Dist: black>=24.10.0; extra == 'all'
Requires-Dist: ipython>=8.30.0; extra == 'all'
Requires-Dist: isort>=5.13.0; extra == 'all'
Requires-Dist: jupyter>=1.1.1; extra == 'all'
Requires-Dist: mypy>=1.13.0; extra == 'all'
Requires-Dist: ollama>=0.4.9; extra == 'all'
Requires-Dist: pre-commit>=4.0.0; extra == 'all'
Requires-Dist: pytest-asyncio>=0.24.0; extra == 'all'
Requires-Dist: pytest-cov>=6.0.0; extra == 'all'
Requires-Dist: pytest-mock>=3.14.0; extra == 'all'
Requires-Dist: pytest>=8.3.0; extra == 'all'
Requires-Dist: requests>=2.32.0; extra == 'all'
Requires-Dist: ruff>=0.8.0; extra == 'all'
Requires-Dist: sentence-transformers>=3.3.0; extra == 'all'
Requires-Dist: torch>=2.5.0; extra == 'all'
Requires-Dist: transformers>=4.47.0; extra == 'all'
Provides-Extra: dev
Requires-Dist: bandit>=1.8.0; extra == 'dev'
Requires-Dist: black>=24.10.0; extra == 'dev'
Requires-Dist: ipython>=8.30.0; extra == 'dev'
Requires-Dist: isort>=5.13.0; extra == 'dev'
Requires-Dist: jupyter>=1.1.1; extra == 'dev'
Requires-Dist: mypy>=1.13.0; extra == 'dev'
Requires-Dist: pre-commit>=4.0.0; extra == 'dev'
Requires-Dist: pytest-asyncio>=0.24.0; extra == 'dev'
Requires-Dist: pytest-cov>=6.0.0; extra == 'dev'
Requires-Dist: pytest-mock>=3.14.0; extra == 'dev'
Requires-Dist: pytest>=8.3.0; extra == 'dev'
Requires-Dist: requests>=2.32.0; extra == 'dev'
Requires-Dist: ruff>=0.8.0; extra == 'dev'
